{
    "Usuarios": [
        {   "id": 1, 
            "nombre":"pepe",
            "email": "pepe@gmail.com",
            "password": 12345
            

        },
        {   "id": 2, 
            "nombre":"juan",
            "email": "juan@gmail.com",
            "password": 23456

        }

    ],


    "Puntaje": [
        {
        "id": 1,
        "puntaje":50, 
        "nombreUsuario": "juan"
        },
        {
        "id": 2,
        "puntaje":65, 
        "nombreUsuario": "juan"
        },
        {
        "id": 3,
        "puntaje":25, 
        "nombreUsuario": "pepe"
        }
    ]

}